doculingo/__init__.py
doculingo/__main__.py
doculingo/main.py
doculingo/common/__init__.py
doculingo/common/settings.py
doculingo/common/translators/__init__.py
doculingo/common/translators/open_ai_translator.py
doculingo/word/__init__.py
doculingo/word/styler.py
doculingo-0.1.1.dist-info/METADATA
doculingo-0.1.1.dist-info/WHEEL
doculingo-0.1.1.dist-info/entry_points.txt
doculingo-0.1.1.dist-info/licenses/license
doculingo-0.1.1.dist-info/RECORD
