Metadata-Version: 2.4
Name: doculingo
Version: 0.1.1
Summary: Tool to translate big documents using LLMs.
Project-URL: homepage, https://github.com/leynier/doculingo
Project-URL: documentation, https://github.com/leynier/doculingo
Project-URL: repository, https://github.com/leynier/doculingo
Project-URL: issues, https://github.com/leynier/doculingo/issues
Author-email: Leynier Gutiérrez González <leynier41@gmail.com>
License-Expression: MIT
License-File: license
Keywords: document,llm,translation
Classifier: Development Status :: 4 - Beta
Classifier: Intended Audience :: Developers
Classifier: License :: OSI Approved :: MIT License
Classifier: Programming Language :: Python :: 3
Classifier: Programming Language :: Python :: 3 :: Only
Classifier: Programming Language :: Python :: 3.12
Requires-Python: >=3.12
Requires-Dist: openai>=1.31.0
Requires-Dist: pydantic-settings>=2.3.0
Requires-Dist: pydantic[all]>=2.7.3
Requires-Dist: python-docx>=1.1.2
Requires-Dist: typer[all]>=0.12.5
